{
  "bench": "attachments",
  "timestamp": "2026-04-30T17:48:45.910Z",
  "hardware": "Darwin Pascals-MacBook-Air.local 25.3.0 Darwin Kernel Version 25.3.0: Wed Jan 28 20:49:24 PST 2026; root:xnu-12377.81.4~5/RELEASE_ARM64_T8132 arm64",
  "serverUrl": "http://localhost:3001",
  "iterations": 5,
  "results": [
    {
      "sizeLabel": "1KB",
      "sizeBytes": 1024,
      "uploadMs": {
        "p50": 2.244082999999989,
        "p95": 3.0013750000000243,
        "p99": 3.0013750000000243,
        "mean": 2.28,
        "min": 1.8510840000000144,
        "max": 3.0013750000000243
      },
      "downloadMs": {
        "p50": 1.303083000000015,
        "p95": 2.1222919999999874,
        "p99": 2.1222919999999874,
        "mean": 1.41,
        "min": 1.0692080000000033,
        "max": 2.1222919999999874
      },
      "roundTripMs": {
        "p50": 3.548166000000009,
        "p95": 5.1267500000000155,
        "p99": 5.1267500000000155,
        "mean": 3.7,
        "min": 2.921291999999994,
        "max": 5.1267500000000155
      },
      "attachmentId": "cmols2kz90000jzu7vna413yh"
    },
    {
      "sizeLabel": "100KB",
      "sizeBytes": 102400,
      "uploadMs": {
        "p50": 1.8325419999999895,
        "p95": 2.0319999999999823,
        "p99": 2.0319999999999823,
        "mean": 1.85,
        "min": 1.7326670000000206,
        "max": 2.0319999999999823
      },
      "downloadMs": {
        "p50": 1.0565829999999892,
        "p95": 1.287040999999988,
        "p99": 1.287040999999988,
        "mean": 1.09,
        "min": 0.9668340000000057,
        "max": 1.287040999999988
      },
      "roundTripMs": {
        "p50": 2.888458000000014,
        "p95": 3.3204589999999996,
        "p99": 3.3204589999999996,
        "mean": 2.94,
        "min": 2.700375000000008,
        "max": 3.3204589999999996
      },
      "attachmentId": "cmols2kzv0006jzu7pjlif67g"
    },
    {
      "sizeLabel": "10MB",
      "sizeBytes": 10485760,
      "uploadMs": {
        "p50": 17.54362500000002,
        "p95": 20.15545800000001,
        "p99": 20.15545800000001,
        "mean": 17.54,
        "min": 15.242500000000007,
        "max": 20.15545800000001
      },
      "downloadMs": {
        "p50": 6.261209000000008,
        "p95": 12.676874999999995,
        "p99": 12.676874999999995,
        "mean": 7.63,
        "min": 5.471749999999986,
        "max": 12.676874999999995
      },
      "roundTripMs": {
        "p50": 25.285416999999995,
        "p95": 31.896417000000042,
        "p99": 31.896417000000042,
        "mean": 25.18,
        "min": 21.016084000000035,
        "max": 31.896417000000042
      },
      "attachmentId": "cmols2l14000cjzu72lu2vlfs"
    }
  ],
  "oversizeCheck": {
    "sizeBytes": 52428801,
    "expectedStatus": 413,
    "actualStatus": 500,
    "passed": false
  }
}